{
  "name": "Hexano Melody",
  "date": "2025-11-18T10:15:16.196Z",
  "notes": [
    {
      "note": "C5",
      "freq": 523.251,
      "time": 0,
      "duration": 300
    },
    {
      "note": "D5",
      "freq": 587.33,
      "time": 400,
      "duration": 300
    },
    {
      "note": "E5",
      "freq": 659.255,
      "time": 800,
      "duration": 300
    },
    {
      "note": "F5",
      "freq": 698.456,
      "time": 1200,
      "duration": 300
    },
    {
      "note": "A5",
      "freq": 880,
      "time": 1600,
      "duration": 600
    },
    {
      "note": "G5",
      "freq": 783.991,
      "time": 2200,
      "duration": 600
    },
    {
      "note": "A5",
      "freq": 880,
      "time": 3200,
      "duration": 600
    },
    {
      "note": "G5",
      "freq": 783.991,
      "time": 3800,
      "duration": 300
    },
    {
      "note": "F5",
      "freq": 698.456,
      "time": 4100,
      "duration": 300
    },
    {
      "note": "E5",
      "freq": 659.255,
      "time": 4400,
      "duration": 600
    },
    {
      "note": "G5",
      "freq": 783.991,
      "time": 5000,
      "duration": 600
    },
    {
      "note": "D5",
      "freq": 587.33,
      "time": 5600,
      "duration": 600
    }
  ]
}