{
  "name": "Hexano Melody",
  "date": "2025-11-17T22:00:35.331Z",
  "notes": [
    {
      "note": "C4",
      "freq": 261.626,
      "time": 0,
      "duration": 266.6719999999914
    },
    {
      "note": "E4",
      "freq": 329.628,
      "time": 416.6750000000029,
      "duration": 283.33899999999267
    },
    {
      "note": "G4",
      "freq": 392,
      "time": 816.68299999999,
      "duration": 333.3399999999965
    },
    {
      "note": "E4",
      "freq": 329.628,
      "time": 1233.3580000000075,
      "duration": 266.6719999999914
    },
    {
      "note": "C4",
      "freq": 261.626,
      "time": 1683.3669999999984,
      "duration": 200.00399999998626
    },
    {
      "note": "E4",
      "freq": 329.628,
      "time": 2150.043000000005,
      "duration": 216.6710000000021
    },
    {
      "note": "G4",
      "freq": 392,
      "time": 2300.046000000002,
      "duration": 516.676999999996
    },
    {
      "note": "E4",
      "freq": 329.628,
      "time": 2883.3910000000033,
      "duration": 516.676999999996
    }
  ]
}